metcalcpy/__init__.py
metcalcpy/agg_eclv.py
metcalcpy/agg_stat.py
metcalcpy/agg_stat_bootstrap.py
metcalcpy/agg_stat_eqz.py
metcalcpy/agg_stat_event_equalize.py
metcalcpy/bootstrap.py
metcalcpy/calc_difficulty_index.py
metcalcpy/compare_images.py
metcalcpy/event_equalize.py
metcalcpy/event_equalize_against_values.py
metcalcpy/piecewise_linear.py
metcalcpy/process_tcrmw.py
metcalcpy/scorecard.py
metcalcpy/sum_stat.py
metcalcpy/validate_mv_python.py
metcalcpy/vertical_interp.py
metcalcpy/contributed/__init__.py
metcalcpy/contributed/blocking_weather_regime/Blocking.py
metcalcpy/contributed/blocking_weather_regime/Blocking_WeatherRegime_util.py
metcalcpy/contributed/blocking_weather_regime/WeatherRegime.py
metcalcpy/contributed/blocking_weather_regime/__init__.py
metcalcpy/contributed/mjo_enso/__init__.py
metcalcpy/contributed/mjo_enso/compute_mjo_enso.py
metcalcpy/contributed/rmm_omi/__init__.py
metcalcpy/contributed/rmm_omi/compute_mjo_indices.py
metcalcpy/contributed/spacetime/__init__.py
metcalcpy/contributed/spacetime/cross_spectra.py
metcalcpy/contributed/spacetime/matsuno_plot.py
metcalcpy/contributed/spacetime/spacetime.py
metcalcpy/contributed/spacetime/spacetime_utils.py
metcalcpy/contributed/tropical_diagnostics/__init__.py
metcalcpy/contributed/tropical_diagnostics/ccew_activity.py
metcalcpy/contributed/tropical_diagnostics/compute_omi_example.py
metcalcpy/contributed/tropical_diagnostics/compute_rmm_example.py
metcalcpy/contributed/tropical_diagnostics/example_kelvin_activity.py
metcalcpy/contributed/tropical_diagnostics/phase_diagram_example.py
metcalcpy/contributed/tropical_diagnostics/utils.py
metcalcpy/pre_processing/__init__.py
metcalcpy/pre_processing/directional_means.py
metcalcpy/pre_processing/waves.py
metcalcpy/util/__init__.py
metcalcpy/util/correlation.py
metcalcpy/util/ctc_statistics.py
metcalcpy/util/eclv_statistics.py
metcalcpy/util/ecnt_statistics.py
metcalcpy/util/grad_statistics.py
metcalcpy/util/mcts_statistics.py
metcalcpy-2.1.dist-info/LICENSE.md
metcalcpy-2.1.dist-info/METADATA
metcalcpy-2.1.dist-info/WHEEL
metcalcpy-2.1.dist-info/top_level.txt
metcalcpy-2.1.dist-info/RECORD
