Metadata-Version: 2.1
Name: metcalcpy
Version: 2.1
Summary: statistics and util package for METplus
Home-page: https://github.com/dtcenter/METcalcpy
Author: METplus
Author-email: met-help@ucar.edu
Classifier: Programming Language :: Python :: 3
Classifier: License :: OSI Approved :: Apache Software License
Classifier: Operating System :: OS Independent
Requires-Python: >=3.10
License-File: LICENSE.md
